datamine/__init__.py
datamine/io.py
datamine/utils.py
datamine/loaders/1qbit.py
datamine/loaders/__init__.py
datamine/loaders/base.py
datamine/loaders/block.py
datamine/loaders/cryptocurrency.py
datamine/loaders/eod.py
datamine/loaders/eris.py
datamine/loaders/fx.py
datamine/loaders/govpx.py
datamine/loaders/liqtool.py
datamine/loaders/orbitalinsight.py
datamine/loaders/rsmetrics.py
datamine/loaders/sofr.py
datamine/loaders/sofrsr.py
datamine/loaders/telluslabs.py
datamine/loaders/tick.py
datamine/loaders/voi.py
datamine-0.21.post2.dist-info/LICENSE
datamine-0.21.post2.dist-info/METADATA
datamine-0.21.post2.dist-info/WHEEL
datamine-0.21.post2.dist-info/top_level.txt
datamine-0.21.post2.dist-info/RECORD
