Metadata-Version: 2.1
Name: datamine
Version: 0.21.post2
Summary: CME Group DataMine Python Package
Home-page: https://github.com/CMEGroup/datamine_python
Author: Aaron Walters
Author-email: aaron.walters@cmegroup.com
Maintainer: Hamza Amjad
Maintainer-email: hamza.amjad@cmegroup.com
License: BSD 3-Clause
Platform: UNKNOWN
Classifier: Development Status :: 3 - Alpha
Classifier: Intended Audience :: Financial and Insurance Industry
Classifier: License :: OSI Approved :: BSD License
Classifier: Programming Language :: Python :: 3.5
Classifier: Programming Language :: Python :: 3.6
Classifier: Programming Language :: Python :: 3.7
Requires-Dist: requests
Requires-Dist: urllib3
Requires-Dist: pandas
Requires-Dist: tqdm
Requires-Dist: futures
